census_geocoder/__init__.py
census_geocoder/__version__.py
census_geocoder/constants.py
census_geocoder/errors.py
census_geocoder/geographies.py
census_geocoder/locations.py
census_geocoder/metaclasses.py
census_geocoder-0.1.0.dist-info/LICENSE
census_geocoder-0.1.0.dist-info/METADATA
census_geocoder-0.1.0.dist-info/WHEEL
census_geocoder-0.1.0.dist-info/top_level.txt
census_geocoder-0.1.0.dist-info/RECORD
