Metadata-Version: 2.1
Name: census-geocoder
Version: 0.1.0
Summary: Unofficial Python Binding for the Census Geocoder API
Home-page: https://census-geocoder.readthedocs.io/en/latest
Author: Insight Industry Inc.
Author-email: software@insightindustry.com
License: MIT
Project-URL: Documentation, https://census-geocoder.readthedocs.io/en/latest
Project-URL: Say Thanks!, https://saythanks.io/to/census-geocoder
Project-URL: Bug Reports, https://github.com/insightindustry/census-geocoder/issues
Project-URL: Source, https://github.com/insightindustry/census-geocoder/
Keywords: census geocoding geocoder reverse geography api
Platform: UNKNOWN
Classifier: Development Status :: 4 - Beta
Classifier: Environment :: Web Environment
Classifier: Operating System :: OS Independent
Classifier: Intended Audience :: Developers
Classifier: Intended Audience :: Education
Classifier: Intended Audience :: Science/Research
Classifier: Topic :: Software Development :: Libraries
Classifier: Topic :: Utilities
Classifier: Topic :: Scientific/Engineering :: GIS
Classifier: Topic :: Scientific/Engineering :: Information Analysis
Classifier: Topic :: Sociology
Classifier: License :: OSI Approved :: MIT License
Classifier: Programming Language :: Python :: 3
Classifier: Programming Language :: Python :: 3.6
Classifier: Programming Language :: Python :: 3.7
Classifier: Programming Language :: Python :: 3.8
Requires-Python: >=3.6, <4
Requires-Dist: validator-collection (>=1.5.0)
Requires-Dist: backoff-utils (>=1.0.1)
Requires-Dist: requests (==2.26.0)
Provides-Extra: dev
Requires-Dist: check-manifest ; extra == 'dev'
Requires-Dist: Sphinx ; extra == 'dev'
Requires-Dist: sphinx-rtd-theme ; extra == 'dev'
Requires-Dist: sphinx-tabs ; extra == 'dev'
Requires-Dist: sphinx-panels ; extra == 'dev'
Requires-Dist: readme-renderer ; extra == 'dev'
Provides-Extra: test
Requires-Dist: coverage ; extra == 'test'
Requires-Dist: pytest ; extra == 'test'
Requires-Dist: pytest-benchmark ; extra == 'test'
Requires-Dist: pytest-cov ; extra == 'test'
Requires-Dist: pytest-xdist ; extra == 'test'
Requires-Dist: tox ; extra == 'test'
Requires-Dist: Sphinx ; extra == 'test'
Requires-Dist: sphinx-rtd-theme ; extra == 'test'
Requires-Dist: sphinx-tabs ; extra == 'test'
Requires-Dist: sphinx-panels ; extra == 'test'
Requires-Dist: codecov ; extra == 'test'
